pandandic/__init__.py
pandandic/base_frame.py
pandandic/column.py
pandandic/column_alias_not_yet_defined_exception.py
pandandic/column_group.py
pandandic/column_group_exception.py
pandandic/column_set.py
pandandic/column_set_members_not_yet_defined_exception.py
pandandic/defined_later.py
pandandic-0.2.2.dist-info/WHEEL
pandandic-0.2.2.dist-info/METADATA
pandandic-0.2.2.dist-info/RECORD
