Metadata-Version: 2.1
Name: pandandic
Version: 0.2.2
Summary: A typed dataframe helper
Home-page: https://github.com/w-martin/pandandic
License: MIT
Author: Will Martin
Author-email: will.st4@gmail.com
Requires-Python: >=3.8,<4.0
Classifier: License :: OSI Approved :: MIT License
Classifier: Programming Language :: Python :: 3
Classifier: Programming Language :: Python :: 3.8
Classifier: Programming Language :: Python :: 3.9
Classifier: Programming Language :: Python :: 3.10
Provides-Extra: all
Provides-Extra: avro
Provides-Extra: extras
Provides-Extra: parquet
Requires-Dist: pandas (>=1.2,<2.0)
Requires-Dist: pandavro (>=1.7.1,<2.0.0); extra == "avro" or extra == "extras" or extra == "all"
Requires-Dist: pyarrow (>=9.0.0,<10.0.0); extra == "parquet" or extra == "extras" or extra == "all"
Requires-Dist: typing_extensions (>=4,<5); python_version < "3.11"
Project-URL: Repository, https://github.com/w-martin/pandandic
